algobattle/__init__.py
algobattle/battle.py
algobattle/cli.py
algobattle/match.py
algobattle/problem.py
algobattle/program.py
algobattle/py.typed
algobattle/templates/__init__.py
algobattle/templates/c/.gitignore
algobattle/templates/c/Dockerfile
algobattle/templates/c/src/CMakeLists.txt
algobattle/templates/c/src/main.c
algobattle/templates/cpp/.gitignore
algobattle/templates/cpp/Dockerfile
algobattle/templates/cpp/src/CMakeLists.txt
algobattle/templates/cpp/src/main.cpp
algobattle/templates/csharp/Dockerfile.jinja
algobattle/templates/csharp/Program.cs
algobattle/templates/csharp/{{program.capitalize()}}.csproj
algobattle/templates/go/.gitignore
algobattle/templates/go/Dockerfile
algobattle/templates/go/go.mod.jinja
algobattle/templates/go/main.go
algobattle/templates/java/.dockerignore
algobattle/templates/java/.gitignore
algobattle/templates/java/Dockerfile.jinja
algobattle/templates/java/pom.xml.jinja
algobattle/templates/java/src/main/java/com/{{team_normalized}}/{{program.capitalize()}}.java.jinja
algobattle/templates/javascript/.gitignore
algobattle/templates/javascript/Dockerfile.jinja
algobattle/templates/javascript/package-lock.json.jinja
algobattle/templates/javascript/package.json.jinja
algobattle/templates/javascript/{{program}}.mjs.jinja
algobattle/templates/plain/Dockerfile.jinja
algobattle/templates/problem.py.jinja
algobattle/templates/python/.gitignore
algobattle/templates/python/Dockerfile.jinja
algobattle/templates/python/pyproject.toml.jinja
algobattle/templates/python/{{program}}.py.jinja
algobattle/templates/rust/.gitignore
algobattle/templates/rust/Cargo.toml.jinja
algobattle/templates/rust/Dockerfile.jinja
algobattle/templates/rust/src/main.rs.jinja
algobattle/templates/typescript/.gitignore
algobattle/templates/typescript/Dockerfile
algobattle/templates/typescript/package-lock.json.jinja
algobattle/templates/typescript/package.json.jinja
algobattle/templates/typescript/src/main.ts
algobattle/templates/typescript/tsconfig.json
algobattle_base-4.3.4.dist-info/METADATA
algobattle_base-4.3.4.dist-info/WHEEL
algobattle_base-4.3.4.dist-info/entry_points.txt
algobattle_base-4.3.4.dist-info/licenses/LICENSE
algobattle_base-4.3.4.dist-info/RECORD
