Metadata-Version: 2.1
Name: algobattle-base
Version: 4.3.4
Summary: The Algobattle lab course package.
Author: Imogen Hergeth, Jan Dreier, Henri Lotze
License: MIT
Classifier: Development Status :: 5 - Production/Stable
Classifier: Environment :: Console
Classifier: Natural Language :: English
Classifier: License :: OSI Approved :: MIT License
Classifier: Programming Language :: Python :: 3
Classifier: Typing :: Typed
Project-URL: Homepage, https://algobattle.org
Project-URL: Documentation, https://algobattle.org/docs
Project-URL: Repository, https://github.com/Benezivas/algobattle
Requires-Python: >=3.11
Requires-Dist: docker>=7.1.0
Requires-Dist: pydantic>=2.11.9
Requires-Dist: anyio>=4.11.0
Requires-Dist: typer>=0.19.2
Requires-Dist: typing-extensions>=4.15.0
Requires-Dist: tomlkit>=0.13.3
Requires-Dist: jinja2>=3.1.6
Provides-Extra: dev
Requires-Dist: ruff>=0.13.2; extra == "dev"
Requires-Dist: mkdocs>=1.5.3; extra == "dev"
Requires-Dist: mkdocs-material>=9.5.3; extra == "dev"
Requires-Dist: pymdown-extensions>=10.7; extra == "dev"
Requires-Dist: mkdocstrings[python]>=0.24.0; extra == "dev"
Requires-Dist: mdx-include>=1.4.2; extra == "dev"
